cada/__init__.py
cada/__main__.py
cada/addons.py
cada/core.py
cada/printer.py
cada/xpath.py
para_cada-1.9.0.dist-info/METADATA
para_cada-1.9.0.dist-info/WHEEL
para_cada-1.9.0.dist-info/entry_points.txt
para_cada-1.9.0.dist-info/RECORD
