Metadata-Version: 2.1
Name: para-cada
Version: 1.9.0
Summary: Executes your command for each file selected using glob expression(s).
Home-page: https://gergelyk.github.io/para-cada
License: MIT
Author: Grzegorz Krason
Author-email: grzegorz.krason@gmail.com
Requires-Python: >=3.8,<4.0
Classifier: License :: OSI Approved :: MIT License
Classifier: Programming Language :: Python :: 3
Classifier: Programming Language :: Python :: 3.8
Classifier: Programming Language :: Python :: 3.9
Classifier: Programming Language :: Python :: 3.10
Classifier: Programming Language :: Python :: 3.11
Requires-Dist: click (>=8.1.7,<9.0.0)
Requires-Dist: click-help-colors (>=0.9.4,<0.10.0)
Requires-Dist: colorama (>=0.4.6,<0.5.0)
Requires-Dist: glob2 (>=0.7,<0.8)
Requires-Dist: humanize (>=4.9.0,<5.0.0)
Requires-Dist: natsort (>=8.4.0,<9.0.0)
Project-URL: Repository, https://github.com/gergelyk/para-cada
